sqlifuzzer.py
sqlifuzzer-0.0.9.dist-info/LICENSE
sqlifuzzer-0.0.9.dist-info/METADATA
sqlifuzzer-0.0.9.dist-info/WHEEL
sqlifuzzer-0.0.9.dist-info/entry_points.txt
sqlifuzzer-0.0.9.dist-info/top_level.txt
sqlifuzzer-0.0.9.dist-info/RECORD
