Metadata-Version: 2.1
Name: sqlifuzzer
Version: 0.0.9
Summary: Python script to fuzz for SQL injection vulnerabilities in URL and input parameters.
Home-page: https://github.com/sapphicart/sqli-fuzzer
Author: Shruti Priya
Author-email: sapphicart <shrutipriya44@gmail.com>
License: MIT License
Project-URL: Homepage, https://github.com/sapphicart/sqli-fuzzer
Project-URL: Issues, https://github.com/sapphicart/sqli-fuzzer/issues
Keywords: python,sqli-vulnerability-scanner,sqlinjection
Classifier: Programming Language :: Python :: 3
Classifier: Operating System :: OS Independent
Requires-Python: >=3.8
License-File: LICENSE
Requires-Dist: requests
Requires-Dist: bs4
Requires-Dist: click
Requires-Dist: urllib3
Requires-Dist: colorama
